{
  "memory": [
    "我們曾經以為民主就是讓每個人都可以說話，直到我們看見他們如何利用這種自由來毀掉自由。",
    "當年我們走上街頭，就是為了抵抗這種假裝民主、實則極權的話術。",
    "社會曾經嘗試包容一切，但我們學會了，包容仇恨就是對善良的背叛。",
    "台灣得來不易的多元與尊重，過去就是被這些人反覆踐踏。",
    "我們試過了對話，他們只會拿善意當軟弱。"
  ],
  "enemy": [
    "這些人不是在參與民主，而是在用民主的皮包裹極權的骨。",
    "反對多元、仇恨自由，卻又最愛打著言論自由的旗號。",
    "這群人不是意見不同，是把整個制度當作武器來攻擊社會。",
    "他們不是批評者，是破壞者，是真正的內部威脅。",
    "假裝理性討論，實際上是帶風向搞滲透。",
    "他們的言論不是在辯論，是在削弱社會的防衛力。",
    "每一次縱容這些人，就讓極端更靠近權力核心一步。",
    "民主不該為仇恨讓路，言論自由不該為惡意背書。"
  ],
  "connection": [
    "{議題}是他們進攻民主社會的破口，我們不能再退讓。",
    "他們假借討論{議題}之名，實則在散播破壞民主的仇恨與謠言。",
    "{議題}的討論若被他們主導，後果將是多元的崩潰。",
    "他們從來不是真的關心{議題}，只是利用它來發動認知戰。",
    "看懂他們怎麼利用{議題}操弄群眾，我們才能做出正確判斷。",
    "這不只是{議題}的戰場，而是整個民主價值的防線。"
  ],
  "action": [
    "出門罷藍委不是懲罰異議，是在保護民主不被極端綁架。",
    "他們不會自我收斂，只有人民站出來才能終結這種惡性循環。",
    "為了讓社會回到理性與秩序，我們別無選擇。",
    "如果今天我們不動手，明天可能就輪到我們被消音。",
    "用選票讓他們知道，民主不是他們拿來濫用的玩具。",
    "守住民主的方式，不是討好極端，而是果斷排除。"
  ],
  "rebuttal": [
    "他們會說我們太激進，但真正激進的是他們要推翻民主規則。",
    "他們會裝可憐，但別忘了，真正被壓迫的是被他們攻擊的人。",
    "他們會說我們壓迫異議，其實是我們拒絕讓惡意騎到正義頭上。",
    "這不是言論自由的問題，而是社會自我防衛的必要。",
    "他們假裝自己是受害者，其實一直在製造受害者。",
    "他們說這是寒蟬效應，但真正讓人寒心的是他們的言行。"
  ]
}
